trazer/__init__.py
trazer/_version.py
trazer/analyzer.py
trazer/export.py
trazer/trace.py
trazer-0.2.1.dist-info/LICENSE
trazer-0.2.1.dist-info/METADATA
trazer-0.2.1.dist-info/WHEEL
trazer-0.2.1.dist-info/top_level.txt
trazer-0.2.1.dist-info/RECORD
