Metadata-Version: 2.1
Name: trazer
Version: 0.2.1
Summary: A lightweight trace analysis framework.
Home-page: https://github.com/starsoi/trazer
Author: Hongyan Zhang
Author-email: starsoi@gmail.com
License: UNKNOWN
Platform: UNKNOWN
Classifier: Programming Language :: Python :: 3.8
Classifier: License :: OSI Approved :: MIT License
Classifier: Operating System :: OS Independent
Classifier: Topic :: Software Development :: Embedded Systems
Classifier: Topic :: Software Development :: Libraries :: Python Modules
Classifier: Intended Audience :: Developers
Requires-Python: >=3.8
License-File: LICENSE
